minlpe/ML.py
minlpe/__init__.py
minlpe/adaptiveSampling.py
minlpe/executors.py
minlpe/geometry.py
minlpe/ihs.py
minlpe-1.0.1.dist-info/METADATA
minlpe-1.0.1.dist-info/WHEEL
minlpe-1.0.1.dist-info/top_level.txt
minlpe-1.0.1.dist-info/RECORD
