Metadata-Version: 2.1
Name: minlpe
Version: 1.0.1
Summary: Adaptive sampling based on the minimization of approximation error Lp norm. MaxLpE is a fast adaptive sampling algorithm with accuracy comparable with the best known adaptive sampling methods: TEAD, LIP, MIPT, EIGF, MASA, SFVCT. Its features include sampling time control and parallel (batch) point generation. The norm parameter p regulates sampling, inclining it either towards local exploitation or, conversely, global exploration
Home-page: https://github.com/gudasergey/minlpe
Author: Sergey Guda, Alexandr Algasov
Author-email: gudasergey@gmail.com
Maintainer: Sergey Guda
Classifier: Programming Language :: Python :: 3
Classifier: License :: OSI Approved :: GNU Lesser General Public License v3 or later (LGPLv3+)
Classifier: Operating System :: OS Independent
Requires-Dist: numpy (>=1.14.3)
Requires-Dist: scikit-learn (>=0.20.0)
Requires-Dist: scipy (>=1.1.0)
Requires-Dist: numba (>=0.38.0)
Requires-Dist: pandas (>=0.23.0)
